happydev/__init__.py
happydev/__main__.py
happydev/dynamic_object_proxy.py
happydev/logging_setup.py
happydev/main.py
happydev/tools.py
happydev/utils/df_comparator.py
happydev-0.1.0.dist-info/METADATA
happydev-0.1.0.dist-info/WHEEL
happydev-0.1.0.dist-info/RECORD
