Metadata-Version: 2.1
Name: happydev
Version: 0.1.0
Requires-Python: >=3.13
Requires-Dist: icecream~=2.1.3
Requires-Dist: loguru~=0.7.2
Requires-Dist: pysnooper~=1.2.1
Requires-Dist: rich~=14.0.0
Requires-Dist: wrapt~=1.16.0
